{
    "project_info": {
        "project_number": "419510197892",
        "project_id": "overseerr-client-app",
        "storage_bucket": "overseerr-client-app.firebasestorage.app"
    },
    "client": [
        {
            "client_info": {
                "mobilesdk_app_id": "1:419510197892:android:b2bb5a17bb55afdc672cd1",
                "android_client_info": {
                    "package_name": "app.lusk.client"
                }
            },
            "oauth_client": [],
            "api_key": [
                {
                    "current_key": "AIzaSyBfe76upJX8Qs754G0XHyNJ1NUMK9m9z5c"
                }
            ],
            "services": {
                "appinvite_service": {
                    "other_platform_oauth_client": []
                }
            }
        },
        {
            "client_info": {
                "mobilesdk_app_id": "1:419510197892:android:5ebb59ff7bd4f519672cd1",
                "android_client_info": {
                    "package_name": "app.lusk.client.debug"
                }
            },
            "oauth_client": [],
            "api_key": [
                {
                    "current_key": "AIzaSyBfe76upJX8Qs754G0XHyNJ1NUMK9m9z5c"
                }
            ],
            "services": {
                "appinvite_service": {
                    "other_platform_oauth_client": []
                }
            }
        }
    ],
    "configuration_version": "1"
}